ci_scripts/__init__.py
ci_scripts/common.py
ci_scripts/npm.py
ci_scripts/php.py
ci_scripts/progstats.py
ci_scripts/release_upload_common.py
ci_scripts/ruby.py
ci_scripts-1.19.0.data/scripts/__play-upload
ci_scripts-1.19.0.data/scripts/changelog-reader
ci_scripts-1.19.0.data/scripts/composer-checkstyle
ci_scripts-1.19.0.data/scripts/composer-docgen
ci_scripts-1.19.0.data/scripts/composer-unittest
ci_scripts-1.19.0.data/scripts/git-mirror-pusher
ci_scripts-1.19.0.data/scripts/github-release-upload
ci_scripts-1.19.0.data/scripts/gitlab-release-upload
ci_scripts-1.19.0.data/scripts/gitstats-gen
ci_scripts-1.19.0.data/scripts/gradle-build-android
ci_scripts-1.19.0.data/scripts/gradle-build-jar
ci_scripts-1.19.0.data/scripts/gradle-dokka
ci_scripts-1.19.0.data/scripts/gradle-jacoco
ci_scripts-1.19.0.data/scripts/gradle-ktlint
ci_scripts-1.19.0.data/scripts/play-upload
ci_scripts-1.19.0.data/scripts/pypi-upload
ci_scripts-1.19.0.data/scripts/python-codestyle-check
ci_scripts-1.19.0.data/scripts/python-static-type-check
ci_scripts-1.19.0.data/scripts/python-unittest
ci_scripts-1.19.0.data/scripts/rdoc-docgen
ci_scripts-1.19.0.data/scripts/ruby-gem-build
ci_scripts-1.19.0.data/scripts/ruby-gem-publish
ci_scripts-1.19.0.data/scripts/ruby-rubocop
ci_scripts-1.19.0.data/scripts/sphinx-docgen
ci_scripts-1.19.0.data/scripts/webext-build
ci_scripts-1.19.0.data/scripts/webext-lint
ci_scripts-1.19.0.data/scripts/webext-version
test/__init__.py
test/test_dummy.py
ci_scripts-1.19.0.dist-info/LICENSE
ci_scripts-1.19.0.dist-info/METADATA
ci_scripts-1.19.0.dist-info/WHEEL
ci_scripts-1.19.0.dist-info/top_level.txt
ci_scripts-1.19.0.dist-info/RECORD
