Metadata-Version: 2.1
Name: ci-scripts
Version: 1.19.0
Summary: Scripts to streamline Gitlab CI builds
Home-page: https://gitlab.namibsun.net/namibsun/python/ci-scripts
Author: Hermann Krumrey
Author-email: hermann@krumreyh.com
License: GNU GPL3
Platform: UNKNOWN
Classifier: License :: OSI Approved :: GNU General Public License v3 (GPLv3)
Requires-Dist: requests
Requires-Dist: typing
Requires-Dist: colorama
